teapod/__init__.py
teapod/scripts/information.py
teapod/scripts/org_import.py
teapod/scripts/pip_update_all.py
teapod/scripts/poetry_add_latest.py
teapod/scripts/poetry_export_requirements.py
teapod/scripts/surge_to_ss.py
teapod-0.3.8.dist-info/entry_points.txt
teapod-0.3.8.dist-info/WHEEL
teapod-0.3.8.dist-info/METADATA
teapod-0.3.8.dist-info/RECORD
