Metadata-Version: 2.1
Name: teapod
Version: 0.3.8
Summary: Teapod.
Author: Yevgnen Koh
Author-email: wherejoystarts@gmail.com
Requires-Python: >=3.8,<4.0
Classifier: Programming Language :: Python :: 3
Classifier: Programming Language :: Python :: 3.10
Classifier: Programming Language :: Python :: 3.8
Classifier: Programming Language :: Python :: 3.9
Requires-Dist: pytoml
Requires-Dist: resworb
Requires-Dist: rich
